LICENSE
py3status_ups_battery_status/__init__.py
py3status_ups_battery_status/ups_battery_status.py
py3status_ups_battery_status-0.1.3.dist-info/entry_points.txt
py3status_ups_battery_status-0.1.3.dist-info/LICENSE
py3status_ups_battery_status-0.1.3.dist-info/WHEEL
py3status_ups_battery_status-0.1.3.dist-info/METADATA
py3status_ups_battery_status-0.1.3.dist-info/RECORD
